bili_stalker_mcp/__init__.py
bili_stalker_mcp/cli.py
bili_stalker_mcp/config.py
bili_stalker_mcp/core.py
bili_stalker_mcp/server.py
bili_stalker_mcp-2.3.dist-info/licenses/LICENSE
bili_stalker_mcp-2.3.dist-info/METADATA
bili_stalker_mcp-2.3.dist-info/WHEEL
bili_stalker_mcp-2.3.dist-info/entry_points.txt
bili_stalker_mcp-2.3.dist-info/top_level.txt
bili_stalker_mcp-2.3.dist-info/RECORD
