Metadata-Version: 2.4
Name: bili_stalker_mcp
Version: 2.3
Summary: MCP Server for getting Bilibili user video updates
Author-email: 222wcnm <2328072813li@gmail.com>
Maintainer-email: 222wcnm <2328072813li@gmail.com>
License-Expression: MIT
Project-URL: Homepage, https://github.com/222wcnm/BiliStalkerMCP
Project-URL: Documentation, https://github.com/222wcnm/BiliStalkerMCP#readme
Project-URL: Repository, https://github.com/222wcnm/BiliStalkerMCP
Project-URL: Issues, https://github.com/222wcnm/BiliStalkerMCP/issues
Project-URL: Changelog, https://github.com/222wcnm/BiliStalkerMCP/releases
Keywords: mcp,bilibili,stalker,video,updates,ai,model-context-protocol
Classifier: Development Status :: 4 - Beta
Classifier: Environment :: Console
Classifier: Intended Audience :: Developers
Classifier: Intended Audience :: End Users/Desktop
Classifier: Operating System :: OS Independent
Classifier: Programming Language :: Python :: 3
Classifier: Programming Language :: Python :: 3.10
Classifier: Programming Language :: Python :: 3.11
Classifier: Programming Language :: Python :: 3.12
Classifier: Topic :: Internet :: WWW/HTTP :: Dynamic Content
Classifier: Topic :: Software Development :: Libraries :: Python Modules
Classifier: Topic :: Multimedia :: Video
Classifier: Topic :: Communications
Requires-Python: >=3.10
License-File: LICENSE
Requires-Dist: bilibili-api-python>=17.1.4
Requires-Dist: fastmcp>=0.4.0
Requires-Dist: mcp[cli]>=1.11.0
Requires-Dist: httpx>=0.25.0
Requires-Dist: async-lru>=2.0.4
Provides-Extra: dev
Requires-Dist: pytest>=7.0.0; extra == "dev"
Requires-Dist: pytest-cov>=4.0.0; extra == "dev"
Requires-Dist: black>=23.0.0; extra == "dev"
Requires-Dist: isort>=5.12.0; extra == "dev"
Requires-Dist: flake8>=6.0.0; extra == "dev"
Requires-Dist: mypy>=1.0.0; extra == "dev"
Dynamic: license-file
